python_demo/__init__.py
python_demo/sort.py
python_demo_wulv-0.1.0.dist-info/METADATA
python_demo_wulv-0.1.0.dist-info/WHEEL
python_demo_wulv-0.1.0.dist-info/RECORD
