Metadata-Version: 2.1
Name: python-demo-wulv
Version: 0.1.0
Summary: 
Author: 无弃
Author-email: wuqi.wl@alibaba-inc.com
Requires-Python: >=3.8,<4.0
Classifier: Programming Language :: Python :: 3
Classifier: Programming Language :: Python :: 3.8
Classifier: Programming Language :: Python :: 3.9
Classifier: Programming Language :: Python :: 3.10
Classifier: Programming Language :: Python :: 3.11
Requires-Dist: requests (>=2.32.3,<3.0.0)
